pygeneral/__init__.py
pygeneral/app_based.py
pygeneral-1.0.0.dist-info/METADATA
pygeneral-1.0.0.dist-info/WHEEL
pygeneral-1.0.0.dist-info/licenses/LICENSE
pygeneral-1.0.0.dist-info/RECORD
